{
  "id": "github-20260720-156",
  "title": "Anjalirajoriya/customer-support-ai",
  "source_url": "https://github.com/Anjalirajoriya/customer-support-ai",
  "source_type": "github_trending",
  "summary": "一个基于AI的客户支持系统，利用自然语言处理技术自动回答用户查询、分类工单并提供个性化回复。核心价值在于提升客服效率，减少人工成本，适用于电商、SaaS等行业的在线客服场景。技术亮点包括意图识别、情感分析和知识库集成。",
  "tags": [
    "Customer Support",
    "NLP",
    "Chatbot",
    "Automation",
    "github"
  ],
  "score": 7,
  "popularity": 0,
  "status": "draft",
  "created_at": "2026-07-20T07:58:41+00:00",
  "updated_at": "2026-07-20T07:58:41+00:00"
}
